hub_toolbox/__init__.py
hub_toolbox/approximate.py
hub_toolbox/centering.py
hub_toolbox/distances.py
hub_toolbox/global_scaling.py
hub_toolbox/goodman_kruskal.py
hub_toolbox/htlogging.py
hub_toolbox/hubness.py
hub_toolbox/hubness_analysis.py
hub_toolbox/intrinsic_dimension.py
hub_toolbox/io.py
hub_toolbox/knn_classification.py
hub_toolbox/local_scaling.py
hub_toolbox/shared_neighbors.py
hub_toolbox/utils.py
hub_toolbox/example_datasets/ABOUT
hub_toolbox/example_datasets/dexter_train.data
hub_toolbox/example_datasets/dexter_train.labels
hub_toolbox-2.5.2.dist-info/METADATA
hub_toolbox-2.5.2.dist-info/RECORD
hub_toolbox-2.5.2.dist-info/WHEEL
hub_toolbox-2.5.2.dist-info/top_level.txt
tests/__init__.py
tests/approximate_test.py
tests/centering_test.py
tests/distances_test.py
tests/goodmankruskal_test.py
tests/hubness_test.py
tests/hubnessanalysis_test.py
tests/intrinsicdim_test.py
tests/io_test.py
tests/knn_test.py
tests/localscaling_test.py
tests/logging_test.py
tests/mutualproximity_test.py
tests/sharednn_test.py
